CCRS_Library/__init__.py
CCRS_Library/TUI/__init__.py
CCRS_Library/TUI/main.py
CCRS_Library/clear_pic/NewMain.py
CCRS_Library/clear_pic/NumVision.pt
CCRS_Library/clear_pic/__init__.py
CCRS_Library/clear_pic/main.py
CCRS_Library/clear_pic/numvision_v3_ccrs_11n.pt
CCRS_Library/get_num/__init__.py
CCRS_Library/get_num/get_num_cls.py
CCRS_Library/get_num/get_num_obb.py
CCRS_Library/get_num/get_num_obj.py
CCRS_Library/get_num/num_class_null_v1.pt
CCRS_Library/get_num/num_class_v2.pt
CCRS_Library/get_num/num_obb_v2.pt
CCRS_Library/get_num/num_obj_v1.pt
CCRS_Library/sql/__init__.py
CCRS_Library/sql/main.py
CCRS_Library/sys_info/__init__.py
CCRS_Library/sys_info/main.py
ccrs_library-2.0.6.11.dist-info/licenses/LICENSE
ccrs_library-2.0.6.11.dist-info/METADATA
ccrs_library-2.0.6.11.dist-info/WHEEL
ccrs_library-2.0.6.11.dist-info/top_level.txt
ccrs_library-2.0.6.11.dist-info/RECORD
