Metadata-Version: 2.4
Name: CCRS_Library
Version: 2.0.6.11
Summary: CCRS_Library 是一个CCRS项目的必要组件，提供数据库快捷操作，剪裁和识别铸字图像功能。
Home-page: 
Author: 林间追风
Author-email: 1324435230@qq.com
License-File: LICENSE
Requires-Dist: rich~=13.9.4
Requires-Dist: opencv-python~=4.10.0.84
Requires-Dist: ultralytics~=8.3.63
Requires-Dist: setuptools~=70.0.0
Requires-Dist: psutil~=6.1.1
Requires-Dist: GPUtil~=1.4.0
Requires-Dist: requests~=2.32.3
Requires-Dist: torch~=2.6.0
Requires-Dist: torchvision~=0.21.0
Requires-Dist: torchaudio~=2.6.0
Requires-Dist: wifi~=0.3.8
Requires-Dist: matplotlib~=3.10.0
Requires-Dist: yolov5~=7.0.14
Dynamic: author
Dynamic: author-email
Dynamic: description
Dynamic: description-content-type
Dynamic: license-file
Dynamic: requires-dist
Dynamic: summary
